aspec/__init__.py
aspec/_modidx.py
aspec/cons.py
aspec/core.py
aspec/utils.py
aspec-0.0.16.dist-info/LICENSE
aspec-0.0.16.dist-info/METADATA
aspec-0.0.16.dist-info/WHEEL
aspec-0.0.16.dist-info/entry_points.txt
aspec-0.0.16.dist-info/top_level.txt
aspec-0.0.16.dist-info/RECORD
