Metadata-Version: 2.1
Name: aspec
Version: 0.0.16
Summary: attribute specificatoin (aspec)
Home-page: https://github.com/dsm-72/aspec
Author: dsm-72
Author-email: sumner.magruder@yale.edu
License: Apache Software License 2.0
Keywords: nbdev jupyter notebook python attr prep util spec attributes preparation data science args autil atil aspec ispec ropts ranked arguments kws
Classifier: Development Status :: 4 - Beta
Classifier: Intended Audience :: Developers
Classifier: Natural Language :: English
Classifier: Programming Language :: Python :: 3.11
Classifier: License :: OSI Approved :: Apache Software License
Requires-Python: >=3.11
License-File: LICENSE
Requires-Dist: quac
Requires-Dist: nchr
Requires-Dist: nlit
Requires-Dist: chck
Requires-Dist: ropts
Requires-Dist: ispec
Provides-Extra: dev
